tp_connected
